audit_log.v
module audit_log(
    input allow_vote,
    input cast_vote,
    input [2:0] voter_index,
    input [1:0] vote_sel,

    output reg [2:0] log_voter0, log_voter1, log_voter2, log_voter3,
    output reg [2:0] log_voter4, log_voter5, log_voter6, log_voter7,

    output reg [1:0] log_vote0, log_vote1, log_vote2, log_vote3,
    output reg [1:0] log_vote4, log_vote5, log_vote6, log_vote7
);

reg [2:0] log_ptr;

initial begin
    log_ptr = 0;
end

always @(posedge cast_vote) begin
    if (allow_vote) begin

        case(log_ptr)

        3'd0: begin log_voter0 = voter_index; log_vote0 = vote_sel; end
        3'd1: begin log_voter1 = voter_index; log_vote1 = vote_sel; end
        3'd2: begin log_voter2 = voter_index; log_vote2 = vote_sel; end
        3'd3: begin log_voter3 = voter_index; log_vote3 = vote_sel; end
        3'd4: begin log_voter4 = voter_index; log_vote4 = vote_sel; end
        3'd5: begin log_voter5 = voter_index; log_vote5 = vote_sel; end
        3'd6: begin log_voter6 = voter_index; log_vote6 = vote_sel; end
        3'd7: begin log_voter7 = voter_index; log_vote7 = vote_sel; end

        endcase

        log_ptr = log_ptr + 1;

    end
end

endmodule

vote_controller.v
module vote_controller(
    input allow_vote,
    input cast_vote,
    input [1:0] vote_sel,

    output reg [7:0] candidate_A_votes,
    output reg [7:0] candidate_B_votes,
    output reg [7:0] candidate_C_votes,
    output reg [7:0] nota_votes
);

initial begin
    candidate_A_votes = 0;
    candidate_B_votes = 0;
    candidate_C_votes = 0;
    nota_votes = 0;
end

always @(posedge cast_vote) begin

    if(allow_vote) begin

        case(vote_sel)

            2'b00: candidate_A_votes = candidate_A_votes + 1;

            2'b01: candidate_B_votes = candidate_B_votes + 1;

            2'b10: candidate_C_votes = candidate_C_votes + 1;

            2'b11: nota_votes = nota_votes + 1;

        endcase

    end

end

endmodule

voter_lock.v
module voter_lock(
    input valid_voter,
    input [2:0] voter_index,
    input cast_vote,
    output reg allow_vote
);

reg voted_flag [0:7];

integer i;

initial begin
    for(i = 0; i < 8; i = i + 1)
        voted_flag[i] = 0;
end

always @(*) begin
    if(valid_voter && voted_flag[voter_index] == 0)
        allow_vote = 1;
    else
        allow_vote = 0;
end

always @(posedge cast_vote) begin
    if(valid_voter && voted_flag[voter_index] == 0)
        voted_flag[voter_index] = 1;
end

endmodule

auth_module.v
/*Database*/
module auth_module(
    input [7:0] biometric_hash,
    input scan,
    output reg valid_voter,
    output reg [2:0] voter_index
);

reg [7:0] voter_db [0:7];

integer i;

initial begin
    voter_db[0] = 8'b10110011;
    voter_db[1] = 8'b01010101;
    voter_db[2] = 8'b11001100;
    voter_db[3] = 8'b00110011;
    voter_db[4] = 8'b11100011;
    voter_db[5] = 8'b00011110;
    voter_db[6] = 8'b10101010;

end

always @(*) begin
    valid_voter = 0;
    voter_index = 0;

    if(scan) begin
        for(i = 0; i < 8; i = i + 1) begin
            if(biometric_hash == voter_db[i]) begin
                valid_voter = 1;
                voter_index = i;
            end
        end
    end
end

endmodule

evm_system_tb.v
module evm_system_tb;

reg [7:0] biometric_hash;
reg scan;
reg cast_vote;
reg [1:0] vote_sel;

wire valid_voter;
wire [2:0] voter_index;
wire allow_vote;

wire [7:0] candidate_A_votes;
wire [7:0] candidate_B_votes;
wire [7:0] candidate_C_votes;
wire [7:0] nota_votes;

/*audit log wires*/
wire [2:0] log_voter0, log_voter1, log_voter2, log_voter3, log_voter4, log_voter5, log_voter6, log_voter7;
wire [1:0] log_vote0, log_vote1, log_vote2, log_vote3, log_vote4, log_vote5, log_vote6, log_vote7;

/* result file handle */
integer file;

/* Authentication */

auth_module auth(
    .biometric_hash(biometric_hash),
    .scan(scan),
    .valid_voter(valid_voter),
    .voter_index(voter_index)
);

/* Voter Lock */

voter_lock lock(
    .valid_voter(valid_voter),
    .voter_index(voter_index),
    .cast_vote(cast_vote),
    .allow_vote(allow_vote)
);

/* Vote Controller */

vote_controller vote(
    .allow_vote(allow_vote),
    .cast_vote(cast_vote),
    .vote_sel(vote_sel),
    .candidate_A_votes(candidate_A_votes),
    .candidate_B_votes(candidate_B_votes),
    .candidate_C_votes(candidate_C_votes),
    .nota_votes(nota_votes)
);

/* Audit Log */

audit_log audit(
    .allow_vote(allow_vote),
    .cast_vote(cast_vote),
    .voter_index(voter_index),
    .vote_sel(vote_sel),

    .log_voter0(log_voter0), .log_voter1(log_voter1),
    .log_voter2(log_voter2), .log_voter3(log_voter3),
    .log_voter4(log_voter4), .log_voter5(log_voter5),
    .log_voter6(log_voter6), .log_voter7(log_voter7),

    .log_vote0(log_vote0), .log_vote1(log_vote1),
    .log_vote2(log_vote2), .log_vote3(log_vote3),
    .log_vote4(log_vote4), .log_vote5(log_vote5),
    .log_vote6(log_vote6), .log_vote7(log_vote7)
);

initial begin

    $dumpfile("evm_wave.vcd");
    $dumpvars(0,evm_system_tb);

    scan = 0;
    cast_vote = 0;
    vote_sel = 0;

    #10;

    /* Voter 0 votes Candidate A */

    scan = 1;
    biometric_hash = 8'b10110011;
    vote_sel = 2'b00;

    #20;

    cast_vote = 1;
    #10;
    cast_vote = 0;

    #30;

    /* Voter 3 votes Candidate B */

    biometric_hash = 8'b00110011;
    vote_sel = 2'b01;

    #20;

    cast_vote = 1;
    #10;
    cast_vote = 0;

    #30;

    /* Voter 4 votes Candidate B */

    biometric_hash = 8'b11100011;
    vote_sel = 2'b01;

    #20;

    cast_vote = 1;
    #10;
    cast_vote = 0;

    #30;
/* Invalid Voter  */

    biometric_hash = 8'b01100110;
    vote_sel = 2'b01;

    #20;

    cast_vote = 1;
    #10;
    cast_vote = 0;

    #30;

    /* Voter 1 votes NOTA */

    biometric_hash = 8'b01010101;
    vote_sel = 2'b11;

    #20;

    cast_vote = 1;
    #10;
    cast_vote = 0;

    #30;

    /* Voter 3 tries to vote again */

    biometric_hash = 8'b00110011;
    vote_sel = 2'b10;

    #20;

    cast_vote = 1;
    #10;
    cast_vote = 0;

    #50;

    /* Write results to file */

    file = $fopen("results.txt","w");

    $fdisplay(file,"CandidateA=%d", candidate_A_votes);
    $fdisplay(file,"CandidateB=%d", candidate_B_votes);
    $fdisplay(file,"CandidateC=%d", candidate_C_votes);
    $fdisplay(file,"NOTA=%d", nota_votes);

    $fclose(file);

    #10 $finish;

end

endmodule

evm_wave.vcd
$date
	Thu Apr 23 10:32:20 2026
$end
$version
	Icarus Verilog
$end
$timescale
	1s
$end
$scope module evm_system_tb $end
$var wire 3 ! voter_index [2:0] $end
$var wire 1 " valid_voter $end
$var wire 8 # nota_votes [7:0] $end
$var wire 3 $ log_voter7 [2:0] $end
$var wire 3 % log_voter6 [2:0] $end
$var wire 3 & log_voter5 [2:0] $end
$var wire 3 ' log_voter4 [2:0] $end
$var wire 3 ( log_voter3 [2:0] $end
$var wire 3 ) log_voter2 [2:0] $end
$var wire 3 * log_voter1 [2:0] $end
$var wire 3 + log_voter0 [2:0] $end
$var wire 2 , log_vote7 [1:0] $end
$var wire 2 - log_vote6 [1:0] $end
$var wire 2 . log_vote5 [1:0] $end
$var wire 2 / log_vote4 [1:0] $end
$var wire 2 0 log_vote3 [1:0] $end
$var wire 2 1 log_vote2 [1:0] $end
$var wire 2 2 log_vote1 [1:0] $end
$var wire 2 3 log_vote0 [1:0] $end
$var wire 8 4 candidate_C_votes [7:0] $end
$var wire 8 5 candidate_B_votes [7:0] $end
$var wire 8 6 candidate_A_votes [7:0] $end
$var wire 1 7 allow_vote $end
$var reg 8 8 biometric_hash [7:0] $end
$var reg 1 9 cast_vote $end
$var reg 1 : scan $end
$var reg 2 ; vote_sel [1:0] $end
$var integer 32 < file [31:0] $end
$scope module audit $end
$var wire 1 9 cast_vote $end
$var wire 2 = vote_sel [1:0] $end
$var wire 3 > voter_index [2:0] $end
$var wire 1 7 allow_vote $end
$var reg 3 ? log_ptr [2:0] $end
$var reg 2 @ log_vote0 [1:0] $end
$var reg 2 A log_vote1 [1:0] $end
$var reg 2 B log_vote2 [1:0] $end
$var reg 2 C log_vote3 [1:0] $end
$var reg 2 D log_vote4 [1:0] $end
$var reg 2 E log_vote5 [1:0] $end
$var reg 2 F log_vote6 [1:0] $end
$var reg 2 G log_vote7 [1:0] $end
$var reg 3 H log_voter0 [2:0] $end
$var reg 3 I log_voter1 [2:0] $end
$var reg 3 J log_voter2 [2:0] $end
$var reg 3 K log_voter3 [2:0] $end
$var reg 3 L log_voter4 [2:0] $end
$var reg 3 M log_voter5 [2:0] $end
$var reg 3 N log_voter6 [2:0] $end
$var reg 3 O log_voter7 [2:0] $end
$upscope $end
$scope module auth $end
$var wire 8 P biometric_hash [7:0] $end
$var wire 1 : scan $end
$var reg 1 " valid_voter $end
$var reg 3 Q voter_index [2:0] $end
$var integer 32 R i [31:0] $end
$upscope $end
$scope module lock $end
$var wire 1 9 cast_vote $end
$var wire 1 " valid_voter $end
$var wire 3 S voter_index [2:0] $end
$var reg 1 7 allow_vote $end
$var integer 32 T i [31:0] $end
$upscope $end
$scope module vote $end
$var wire 1 7 allow_vote $end
$var wire 1 9 cast_vote $end
$var wire 2 U vote_sel [1:0] $end
$var reg 8 V candidate_A_votes [7:0] $end
$var reg 8 W candidate_B_votes [7:0] $end
$var reg 8 X candidate_C_votes [7:0] $end
$var reg 8 Y nota_votes [7:0] $end
$upscope $end
$upscope $end
$enddefinitions $end
#0
$dumpvars
b0 Y
b0 X
b0 W
b0 V
b0 U
b1000 T
b0 S
bx R
b0 Q
bx P
bx O
bx N
bx M
bx L
bx K
bx J
bx I
bx H
bx G
bx F
bx E
bx D
bx C
bx B
bx A
bx @
b0 ?
b0 >
b0 =
bx <
b0 ;
0:
09
bx 8
07
b0 6
b0 5
b0 4
bx 3
bx 2
bx 1
bx 0
bx /
bx .
bx -
bx ,
bx +
bx *
bx )
bx (
bx '
bx &
bx %
bx $
b0 #
0"
b0 !
$end
#10
17
1"
b1000 R
b10110011 8
b10110011 P
1:
#30
07
b1 6
b1 V
b1 ?
b0 3
b0 @
b0 +
b0 H
19
#40
09
#70
17
b11 !
b11 >
b11 Q
b11 S
b1000 R
1"
b1 ;
b1 =
b1 U
b110011 8
b110011 P
#90
07
b10 ?
b1 2
b1 A
b11 *
b11 I
b1 5
b1 W
19
#100
09
#130
17
b1000 R
b100 !
b100 >
b100 Q
b100 S
1"
b11100011 8
b11100011 P
#150
07
b10 5
b10 W
b11 ?
b1 1
b1 B
b100 )
b100 J
19
#160
09
#190
b1000 R
b0 !
b0 >
b0 Q
b0 S
0"
b1100110 8
b1100110 P
#210
19
#220
09
#250
17
b1 !
b1 >
b1 Q
b1 S
1"
b1000 R
b11 ;
b11 =
b11 U
b1010101 8
b1010101 P
#270
07
b1 #
b1 Y
b100 ?
b11 0
b11 C
b1 (
b1 K
19
#280
09
#310
b1000 R
b11 !
b11 >
b11 Q
b11 S
1"
b10 ;
b10 =
b10 U
b110011 8
b110011 P
#330
19
#340
09
#390
b10000000000000000000000000000011 <
